logging2slack/__init__.py
logging2slack/slack_logger.py
logging2slack-2.0.0.dist-info/METADATA
logging2slack-2.0.0.dist-info/WHEEL
logging2slack-2.0.0.dist-info/licenses/LICENSE
logging2slack-2.0.0.dist-info/RECORD
